piko/__init__.py
piko/adom.py
piko/app.py
piko/browser.py
piko/config.py
piko/input_handler.py
piko/pieces.py
piko/renderer.py
piko/util.py
piko/vector.py
piko/window.py
piko/adom/__init__.py
piko/adom/constants.py
piko/adom/document.py
piko/adom/elements.py
piko/adom/parsers.py
piko/adom/utils.py
piko/local/welcome.xml
piko/rendering/__init__.py
piko/rendering/border_util.py
piko/rendering/borders.py
piko/rendering/element_util.py
piko/rendering/render.py
piko/rendering/style.py
piko/rendering/style_constants.py
piko/rendering/text_util.py
piko/rendering/util.py
pikobrowser/__init__.py
pikobrowser/__main__.py
pikobrowser-0.2.27.data/scripts/piko
pikobrowser-0.2.27.dist-info/LICENSE
pikobrowser-0.2.27.dist-info/METADATA
pikobrowser-0.2.27.dist-info/WHEEL
pikobrowser-0.2.27.dist-info/entry_points.txt
pikobrowser-0.2.27.dist-info/top_level.txt
pikobrowser-0.2.27.dist-info/RECORD
